MANIFEST.in
README.md
setup.cfg
setup.py
slacksecrets/__init__.py
slacksecrets/cli.py
slacksecrets/main.py
slacksecrets/models.py
slacksecrets/secrets.py
slacksecrets/slackwrapper.py
slacksecrets/utils.py
slacksecrets.egg-info/PKG-INFO
slacksecrets.egg-info/SOURCES.txt
slacksecrets.egg-info/dependency_links.txt
slacksecrets.egg-info/entry_points.txt
slacksecrets.egg-info/requires.txt
slacksecrets.egg-info/top_level.txt
slacksecrets/rules/amazon_access_key_id.yar
slacksecrets/rules/amazon_mws.yar
slacksecrets/rules/amazon_secret_access_key.yar
slacksecrets/rules/facebook_access_token.yar
slacksecrets/rules/generic_password.yar
slacksecrets/rules/gitlab_ci_reg_token.yar
slacksecrets/rules/gitlab_generic_token.yar
slacksecrets/rules/gitlab_pat_api_token.yar
slacksecrets/rules/gitlab_pat_generic.yar
slacksecrets/rules/google_cloud_api_key.yar
slacksecrets/rules/google_oauth_api_id.yar
slacksecrets/rules/mailchimp_api_key.yar
slacksecrets/rules/mailgun_api_key.yar
slacksecrets/rules/phone_number.yar
slacksecrets/rules/picatic_api_key.yar
slacksecrets/rules/shodan_api_key.yar
slacksecrets/rules/slack_api_token.yar
slacksecrets/rules/slack_webhook.yar
slacksecrets/rules/social_security_number.yar
slacksecrets/rules/square_access_token.yar
slacksecrets/rules/square_oauth_token.yar
slacksecrets/rules/ssh_private_key.yar
slacksecrets/rules/stripe_api_keys.yar
slacksecrets/rules/twilio_api_key.yar
slacksecrets/rules/twitter_api_key.yar
slacksecrets/rules/uri_user_pass.yar