Metadata-Version: 1.2
Name: slacksecrets
Version: 0.1.0a1
Summary: Uncover credentials, API tokens, and other sensitive content in your Slack instance.
Home-page: https://github.com/pseudo-security/slacksecrets
Author: pseudo-security
Author-email: me@pseudo-security.io
License: GPLv3
Keywords: slack secrets api credentials tokens
Platform: UNKNOWN
Classifier: Development Status :: 3 - Alpha
Classifier: License :: OSI Approved :: GNU General Public License v3 (GPLv3)
Classifier: Topic :: Security
Classifier: Topic :: System :: Monitoring
Classifier: Topic :: Communications :: Chat
Classifier: Topic :: Utilities
Classifier: Programming Language :: Python :: 3
Requires-Python: >=3.5
